ipynbname/__init__.py
ipynbname-2025.8.0.0.dist-info/licenses/LICENSE
ipynbname-2025.8.0.0.dist-info/METADATA
ipynbname-2025.8.0.0.dist-info/WHEEL
ipynbname-2025.8.0.0.dist-info/top_level.txt
ipynbname-2025.8.0.0.dist-info/RECORD
