Metadata-Version: 2.4
Name: ipynbname
Version: 2025.8.0.0
Summary: Simply returns either notebook filename or the full path to the notebook when run from Jupyter notebook in browser.
Home-page: https://github.com/msm1089/ipynbname
Author: Mark McPherson
Author-email: msm1089@yahoo.co.uk
License: MIT
Keywords: jupyter,notebook,filename
Classifier: Operating System :: OS Independent
Classifier: Development Status :: 4 - Beta
Classifier: Framework :: Jupyter
Classifier: Topic :: Utilities
Classifier: License :: OSI Approved :: MIT License
Requires-Python: >=3.4
License-File: LICENSE
Requires-Dist: ipykernel
Dynamic: author
Dynamic: author-email
Dynamic: classifier
Dynamic: description
Dynamic: description-content-type
Dynamic: home-page
Dynamic: keywords
Dynamic: license
Dynamic: license-file
Dynamic: requires-dist
Dynamic: requires-python
Dynamic: summary
